{
    "completions": [
        {
            "id": 1001,
            "lead_time": 2.274,
            "result": [
                {
                    "from_name": "sentiment",
                    "id": "aCQSv3xhJE",
                    "to_name": "text",
                    "type": "choices",
                    "value": {
                        "choices": [
                            "Providing Service/Feature",
                            "Service Operation and Security"
                        ]
                    }
                }
            ],
            "user": "nyhplhqh"
        }
    ],
    "data": {
        "reviewText": "The main reason we use your information is <b>to deliver and improve our services</b>."
    },
    "id": 1,
    "predictions": [],
    "task_path": "/Users/mayakhanna/Desktop/research/label-studio/labeling_project/tasks.json"
}